bleak_pythonista/__init__.py
bleak_pythonista/py.typed
bleak_pythonista/args/__init__.py
bleak_pythonista/args/pythonistacb.py
bleak_pythonista/backend/__init__.py
bleak_pythonista/backend/pythonistacb/CentralManager.py
bleak_pythonista/backend/pythonistacb/__init__.py
bleak_pythonista/backend/pythonistacb/_fake_cb.py
bleak_pythonista/backend/pythonistacb/client.py
bleak_pythonista/backend/pythonistacb/scanner.py
bleak_pythonista/backend/pythonistacb/types.py
bleak_pythonista/backend/pythonistacb/utils.py
bleak_pythonista-0.1.2.dist-info/licenses/LICENSE
bleak_pythonista-0.1.2.dist-info/METADATA
bleak_pythonista-0.1.2.dist-info/WHEEL
bleak_pythonista-0.1.2.dist-info/top_level.txt
bleak_pythonista-0.1.2.dist-info/RECORD
