Metadata-Version: 2.4
Name: bleak-pythonista
Version: 0.1.2
Summary: bleak compatible pythonista.cb backend
Author: Dmytro Yaroshenko
License: MIT License
Project-URL: Homepage, https://github.com/o-murphy/bleak-pythonista
Project-URL: Bug Reports, https://github.com/o-murphy/bleak-pythonista/issues
Project-URL: Source, https://github.com/o-murphy/bleak-pythonista
Keywords: bleak,python,pythonista,ble
Classifier: Intended Audience :: Developers
Classifier: Natural Language :: English
Classifier: Programming Language :: Python
Classifier: Topic :: Software Development :: Libraries :: Python Modules
Classifier: Programming Language :: Python :: 3
Classifier: Programming Language :: Python :: 3 :: Only
Classifier: Programming Language :: Python :: 3.9
Classifier: Programming Language :: Python :: 3.10
Classifier: Programming Language :: Python :: 3.11
Classifier: Programming Language :: Python :: 3.12
Classifier: Programming Language :: Python :: 3.13
Classifier: Programming Language :: Python :: Implementation :: CPython
Requires-Python: >=3.9
License-File: LICENSE
Requires-Dist: bleak>=1.0.1
Requires-Dist: typing-extensions>=4.14.1
Dynamic: license-file
